yokkaichi/Checker.py
yokkaichi/IP2L_Manager.py
yokkaichi/Printer.py
yokkaichi/Results.py
yokkaichi/ServerScan.py
yokkaichi/__init__.py
yokkaichi/__main__.py
yokkaichi/config_loader.py
yokkaichi/env_loader.py
yokkaichi/port_parser.py
yokkaichi/constants/__init__.py
yokkaichi/enums/_IP2LocDBStatus.py
yokkaichi/enums/_IP2LocManagerUserAnswers.py
yokkaichi/enums/_OfflinePrintingModes.py
yokkaichi/enums/_Platforms.py
yokkaichi/enums/_ScanTypes.py
yokkaichi/enums/__init__.py
yokkaichi/structs/_CFG.py
yokkaichi/structs/_EnvVariables.py
yokkaichi/structs/_MinecraftServer.py
yokkaichi/structs/__init__.py
yokkaichi_tests/__init__.py
yokkaichi_tests/__main__.py
yokkaichi_tests/test_config_loader.py
yokkaichi_tests/test_env_loader.py
yokkaichi_tests/test_port_parser.py
yokkaichi_tests/test_printer.py
yokkaichi-1.7.dist-info/LICENSE.txt
yokkaichi-1.7.dist-info/METADATA
yokkaichi-1.7.dist-info/WHEEL
yokkaichi-1.7.dist-info/entry_points.txt
yokkaichi-1.7.dist-info/top_level.txt
yokkaichi-1.7.dist-info/RECORD
