Metadata-Version: 2.1
Name: yokkaichi
Version: 1.7
Summary: Shodan-like server scanner for Minecraft (formely mcserverscanner)
Home-page: https://github.com/Oreeeee/yokkaichi
Author: Oreeeee
License: MIT
Classifier: Environment :: Console
Classifier: License :: OSI Approved :: MIT License
Classifier: Natural Language :: English
Classifier: Operating System :: OS Independent
Classifier: Programming Language :: Python :: 3.8
Classifier: Programming Language :: Python :: 3.9
Classifier: Programming Language :: Python :: 3.10
Classifier: Programming Language :: Python :: 3.11
Classifier: Programming Language :: Python :: Implementation :: CPython
License-File: LICENSE.txt
Requires-Dist: rich ==13.4.2
Requires-Dist: mcstatus ==11.0.0
Requires-Dist: IP2Location ==8.10.0
Requires-Dist: pyScannerWrapper ==0.2.1
Requires-Dist: tomli ==2.0.1 ; python_version < "3.11"
Provides-Extra: testing
Requires-Dist: pytest ; extra == 'testing'
